AUTHORS.rst
CONTRIBUTING.rst
HISTORY.rst
LICENSE
MANIFEST.in
README.rst
setup.cfg
setup.py
pygmount/__init__.py
pygmount/__init__.pyc
pygmount.egg-info/PKG-INFO
pygmount.egg-info/SOURCES.txt
pygmount.egg-info/dependency_links.txt
pygmount.egg-info/entry_points.txt
pygmount.egg-info/not-zip-safe
pygmount.egg-info/requires.txt
pygmount.egg-info/top_level.txt
pygmount/bin/__init__.py
pygmount/bin/__init__.pyc
pygmount/bin/mount_smb_shares.py
pygmount/bin/mount_smb_shares.pyc
pygmount/bin/sudoers_conf.py
pygmount/media/mount-smb-shares.desktop
pygmount/media/pygmount.rc.example
pygmount/utils/__init__.py
pygmount/utils/__init__.pyc
pygmount/utils/mount.py
pygmount/utils/mount.pyc
pygmount/utils/utils.py
pygmount/utils/utils.pyc
tests/__init__.py
tests/test_pygmount.py
thirdparty/PyZenity-0.1.7.tar.gz