Metadata-Version: 1.1
Name: pygmount
Version: 0.9.3
Summary: Software for graphical mount network shares.
Home-page: https://github.com/simodalla/pygmount
Author: Simone Dalla
Author-email: simodalla@gmail.com
License: BSD
Keywords: pygmount samba zenity pyzenity gnome mint
Platform: UNKNOWN
Classifier: Development Status :: 4 - Beta
Classifier: Environment :: Console
Classifier: Environment :: X11 Applications :: GTK
Classifier: Intended Audience :: End Users/Desktop
Classifier: Intended Audience :: Other Audience
Classifier: Intended Audience :: Developers
Classifier: License :: OSI Approved :: BSD License
Classifier: Natural Language :: English
Classifier: Natural Language :: Italian
Classifier: Operating System :: POSIX :: Linux
Classifier: Programming Language :: Python :: 2
Classifier: Programming Language :: Python :: 2.6
Classifier: Programming Language :: Python :: 2.7
Classifier: Programming Language :: Python :: 3
Classifier: Programming Language :: Python :: 3.3
Classifier: Topic :: Desktop Environment
Classifier: Topic :: Desktop Environment :: Gnome
Classifier: Topic :: Office/Business
Classifier: Topic :: System
Classifier: Topic :: System :: Networking
Classifier: Topic :: System :: Shells
Classifier: Topic :: Utilities
